README.md
setup.py
singlet/__init__.py
singlet/_version.py
singlet/config.py
singlet/featuresheet.py
singlet/samplesheet.py
singlet.egg-info/PKG-INFO
singlet.egg-info/SOURCES.txt
singlet.egg-info/dependency_links.txt
singlet.egg-info/requires.txt
singlet.egg-info/top_level.txt
singlet/counts_table/__init__.py
singlet/counts_table/counts_table.py
singlet/counts_table/counts_table_sparse.py
singlet/counts_table/counts_table_xarray.py
singlet/dataset/__init__.py
singlet/dataset/cluster.py
singlet/dataset/correlations.py
singlet/dataset/dimensionality.py
singlet/dataset/feature_selection.py
singlet/dataset/fit.py
singlet/dataset/graph.py
singlet/dataset/plot.py
singlet/dataset/plugins.py
singlet/io/__init__.py
singlet/io/csv/__init__.py
singlet/io/googleapi/__init__.py
singlet/io/googleapi/samplesheet.py
singlet/io/loom/__init__.py
singlet/io/npz/__init__.py
singlet/io/pickle/__init__.py
singlet/utils/__init__.py
singlet/utils/cache.py