Metadata-Version: 1.2
Name: singlet
Version: 0.5
Summary: Single cell RNA Seq analysis
Home-page: https://github.com/iosonofabio/singlet
Author: Fabio Zanini
Author-email: fabio.zanini@stanford.edu
Maintainer: Fabio Zanini
Maintainer-email: fabio.zanini@stanford.edu
License: GPL3
Platform: UNKNOWN
Classifier: Development Status :: 3 - Alpha
Classifier: Topic :: Scientific/Engineering :: Bio-Informatics
Classifier: Intended Audience :: Developers
Classifier: Intended Audience :: Science/Research
Classifier: License :: OSI Approved :: GNU General Public License (GPL)
Classifier: Operating System :: POSIX
Classifier: Programming Language :: Python
